pyramid_redirect/__init__.py
pyramid_redirect-0.4.dist-info/COPYING.txt
pyramid_redirect-0.4.dist-info/METADATA
pyramid_redirect-0.4.dist-info/WHEEL
pyramid_redirect-0.4.dist-info/top_level.txt
pyramid_redirect-0.4.dist-info/RECORD
