Metadata-Version: 2.1
Name: pyramid-redirect
Version: 0.4
Summary: Small Pyramid extension for redirecting urls
Home-page: https://github.com/teamniteo/pyramid_redirect
Author: Niteo
Author-email: info@niteo.co
License: BSD
Keywords: pyramid redirect pylons web
Platform: UNKNOWN
Classifier: Operating System :: OS Independent
Classifier: License :: OSI Approved :: BSD License
Classifier: Programming Language :: Python
Classifier: Development Status :: 4 - Beta
Classifier: Intended Audience :: Developers
Classifier: Framework :: Pylons
Classifier: Topic :: Internet :: WWW/HTTP
Classifier: Topic :: Internet :: WWW/HTTP :: WSGI
Classifier: Topic :: Software Development :: Libraries :: Python Modules
Requires-Dist: pyramid (>=1.3a6)
